{"title": "Seth Meyers Tears Into Donald Trump\u2019s 'Crazy' Tweets During James Comey Hearing", "content": "Seth Meyers dissected President Donald Trump\u2019s tweets during FBI director James Comey\u2019s congressional hearing on Monday.\nThe \u201cLate Night\u201d host described Comey\u2019s revelation that his agency was investigating possible ties\u00a0between Trump associates and Russian government officials as\u00a0\u201ca huge, huge deal.\u201d\u00a0But \u201ceven crazier,\u201d Meyers noted, was that as the hearing was ongoing, Trump tweeted this from the president\u2019s official account:\nWhen Comey was quizzed over Trump\u2019s false claim, Meyers riffed on the surreal nature of witnesses in a hearing \u201cfact-checking the president\u2019s tweets about that hearing during a hearing.\u201d\n\u201cAll of this, of course, raises the question once again of where the president gets his information,\u201d said Meyers, suggesting that \u201cwe are now at the point where the crazy things the president says are making their way into the halls of Congress, and wasting the time of allies, intelligence officials and the FBI director.\u201d\n\nCheck out the full segment above.", "date": "\n03/21/2017", "href": "https://www.huffpost.com/entry/seth-meyers-donald-trump-comey-hearing_n_58d0d371e4b0ec9d29ded0ce", "tags": "hearing seth officials meyers comey \u201d trump donald james tweets fbi tears"}