{"title": "Who is standing in the EU elections?", "content": "The leaders of the SDLP and the Alliance Party are to run in the European Parliament election race.\nIt is expected the UK will participate in the EU election on 23 May after a new Brexit date was set for 31 October.\nOutgoing MEPs Martina Anderson from Sinn F\u00e9in and the DUP's Diane Dodds are standing for re-election.\nFormer Ulster Unionist minister Danny Kennedy has launched his candidacy after the party's MEP Jim Nicholson decided to step down.\nThe SDLP leader Colum Eastwood and his Alliance Party counterpart Naomi Long have declared that they will stand as candidates.\nThe TUV leader Jim Allister has also confirmed that he will stand in the European Parliament election.\nThe Green Party has confirmed party leader Clare Bailey as its candidate.\nUKIP has announced it is running Robert Hill as a candidate in Northern Ireland.\nThe Conservative Party has announced its candidate will be Amandeep Singh Bhogal. \nThe DUP and Sinn F\u00e9in claimed more than 45% of the vote combined in the 2014 poll and are expected to retain their seats.\nBut the battle for the third seat could be close.\nMr Nicholson claimed his seat for the Ulster Unionists last time after securing more than 2,000 extra first preference votes than the SDLP's Alex Attwood.\nHe was elected on the eighth count when the gap widened to slightly more than 40,000 votes after transfers.\nWomen's Coalition founder and former deputy speaker of the Northern Ireland Assembly Jane Morrice is also set to contest the election as an independent candidate.\nIndependent candidate Neil McCann will also contest the election. \nFormer SDLP leader Mark Durkan is hoping to win a seat for Fine Gael in Dublin.", "date": "25 April 2019", "href": "https://www.bbc.com/news/uk-northern-ireland-47953086", "tags": "european election eu candidate standing party former elections alliance leader also sdlp seat"}